inceptionlogger/__init__.py
inceptionlogger/logging_inc.py
inceptionlogger/middleware_inc.py
inceptionlogger/settings_inc.py
inceptionlogger-0.2.4.dist-info/LICENSE
inceptionlogger-0.2.4.dist-info/METADATA
inceptionlogger-0.2.4.dist-info/WHEEL
inceptionlogger-0.2.4.dist-info/top_level.txt
inceptionlogger-0.2.4.dist-info/RECORD
