Metadata-Version: 2.1
Name: inceptionlogger
Version: 0.2.4
Summary: inceptionlogger is a package that allows you to log your application to graylog
Home-page: https://github.com/KhaduaBloom/inceptionforcepackages/tree/main/PythonPackage/inceptionLogger
Author: KhaduaBloom
Author-email: khaduabloom@gmail.com
Classifier: Programming Language :: Python :: 3
Classifier: License :: OSI Approved :: MIT License
Classifier: Operating System :: OS Independent
Requires-Python: >=3.13.0
License-File: LICENSE
Requires-Dist: graypy==2.1.0
Requires-Dist: psutil==6.1.0
Requires-Dist: fastapi
Requires-Dist: uvicorn
Requires-Dist: pydantic-settings
